boron/__init__.py
boron/cli.py
boron/configuration.py
boron/errors.py
boron/handler.py
boron/text.py
boron/wsgi.py
boron-1.0.0a3.dist-info/METADATA
boron-1.0.0a3.dist-info/RECORD
boron-1.0.0a3.dist-info/WHEEL
boron-1.0.0a3.dist-info/entry_points.txt
boron-1.0.0a3.dist-info/top_level.txt
